GeneCluster/DataProcess.py
GeneCluster/__init__.py
GeneCluster/cluster.py
GeneCluster/main.py
GeneCluster/utils.py
GeneCluster/models/__init__.py
GeneCluster/models/sppCNN.py
tests/__init__.py
tests/test_GeneCluster.py
GeneCluster-0.1.1.dist-info/LICENSE
GeneCluster-0.1.1.dist-info/METADATA
GeneCluster-0.1.1.dist-info/WHEEL
GeneCluster-0.1.1.dist-info/entry_points.txt
GeneCluster-0.1.1.dist-info/top_level.txt
GeneCluster-0.1.1.dist-info/RECORD
