Metadata-Version: 2.1
Name: GeneCluster
Version: 0.1.1
Summary: A gene clustering model using deep learning
Home-page: https://github.com/Byting820/GeneCluster
Author: Byting
Author-email: yutingya820@163.com
License: UNKNOWN
Platform: UNKNOWN
Classifier: Programming Language :: Python :: 3
Classifier: License :: OSI Approved :: MIT License
Classifier: Operating System :: OS Independent
Requires-Python: >=3.8
Requires-Dist: torch
Requires-Dist: torchvision
Requires-Dist: numpy
Requires-Dist: pandas
Requires-Dist: umap-learn
Requires-Dist: matplotlib
Requires-Dist: scikit-learn
Requires-Dist: argparse
